yabgp/__init__.py
yabgp/config.py
yabgp/hooks.py
yabgp/log.py
yabgp/tlv.py
yabgp/agent/__init__.py
yabgp/agent/cmd.py
yabgp/api/__init__.py
yabgp/api/app.py
yabgp/api/code.py
yabgp/api/config.py
yabgp/api/utils.py
yabgp/api/v1.py
yabgp/common/__init__.py
yabgp/common/afn.py
yabgp/common/constants.py
yabgp/common/exception.py
yabgp/common/flag.py
yabgp/common/safn.py
yabgp/common/tlv.py
yabgp/core/__init__.py
yabgp/core/factory.py
yabgp/core/fsm.py
yabgp/core/protocol.py
yabgp/core/timer.py
yabgp/handler/__init__.py
yabgp/handler/default_handler.py
yabgp/message/__init__.py
yabgp/message/keepalive.py
yabgp/message/notification.py
yabgp/message/open.py
yabgp/message/route_refresh.py
yabgp/message/update.py
yabgp/message/attribute/__init__.py
yabgp/message/attribute/aggregator.py
yabgp/message/attribute/aspath.py
yabgp/message/attribute/atomicaggregate.py
yabgp/message/attribute/clusterlist.py
yabgp/message/attribute/community.py
yabgp/message/attribute/extcommunity.py
yabgp/message/attribute/localpref.py
yabgp/message/attribute/med.py
yabgp/message/attribute/mpreachnlri.py
yabgp/message/attribute/mpunreachnlri.py
yabgp/message/attribute/nexthop.py
yabgp/message/attribute/origin.py
yabgp/message/attribute/originatorid.py
yabgp/message/attribute/pmsitunnel.py
yabgp/message/attribute/tunnelencaps.py
yabgp/message/attribute/linkstate/__init__.py
yabgp/message/attribute/linkstate/linkstate.py
yabgp/message/attribute/linkstate/link/__init__.py
yabgp/message/attribute/linkstate/link/adj_seg_id.py
yabgp/message/attribute/linkstate/link/admingroup.py
yabgp/message/attribute/linkstate/link/igp_metric.py
yabgp/message/attribute/linkstate/link/lan_adj_sid.py
yabgp/message/attribute/linkstate/link/link_identifiers.py
yabgp/message/attribute/linkstate/link/link_msd.py
yabgp/message/attribute/linkstate/link/link_name.py
yabgp/message/attribute/linkstate/link/max_bw.py
yabgp/message/attribute/linkstate/link/max_rsv_bw.py
yabgp-0.5.0.dist-info/DESCRIPTION.rst
yabgp-0.5.0.dist-info/entry_points.txt
yabgp-0.5.0.dist-info/METADATA
yabgp-0.5.0.dist-info/metadata.json
yabgp-0.5.0.dist-info/pbr.json
yabgp-0.5.0.dist-info/RECORD
yabgp-0.5.0.dist-info/top_level.txt
yabgp-0.5.0.dist-info/WHEEL
