Metadata-Version: 2.0
Name: yabgp
Version: 0.5.0
Summary: Yet Another Border Gateway Protocol Python Implementation
Home-page: http://smartbgp.github.io/
Author: SmartBGP project team
Author-email: xiaoquwl@gmail.com
License: Apache License 2.0
Keywords: BGP
Requires-Dist: pbr (==2.0.0)
Requires-Dist: oslo.config (==2.1.0)
Requires-Dist: Twisted (==16.0.0)
Requires-Dist: Flask (==0.10.1)
Requires-Dist: Flask-HTTPAuth (==2.5.0)
Requires-Dist: netaddr (>=0.7.12)
Requires-Dist: future (>=0.16.0)
